LICENSE
MANIFEST.in
README.md
setup.py
cellml.egg-info/PKG-INFO
cellml.egg-info/SOURCES.txt
cellml.egg-info/dependency_links.txt
cellml.egg-info/entry_points.txt
cellml.egg-info/not-zip-safe
cellml.egg-info/requires.txt
cellml.egg-info/top_level.txt
models/__init__.py
models/cnn-simple-model-1560191984.1229792.h5
models/cnn-simple-model-1560265830.333636.h5
models/cnn-simple-model.json
src/__init__.py
src/cli.py
src/cell_processing/__init__.py
src/cell_processing/process_image_folder.py
src/data/__init__.py
src/data/compare_segmentation.py
src/data/utils.py
src/data/segmentation/__init__.py
src/data/segmentation/segment_cells_10.py
src/data/segmentation/segment_cells_2p5.py
src/data/segmentation/segment_cells_5.py
src/models/__init__.py
src/models/train/__init__.py
src/models/train/cnn_on_vgg16_bottleneck.py
src/models/train/cnn_simple.py
src/models/train/cnn_transfer.py
src/models/utils/__init__.py
src/models/utils/loading_models.py
src/models/utils/predict_from_model.py
src/visualization/__init__.py
src/visualization/image_processing_overlay.py
src/visualization/process_plotting.py
src/visualization/training_plot.py