Metadata-Version: 2.1
Name: cellml
Version: 0.1.1
Summary: Integrated tool to measure the shapes of adherent cells on posts. 
Home-page: https://github.com/caromccue/CellML
Author: Caroline McCue
Author-email: caroline.t.mccue@gmail.com
License: GPLv3
Platform: UNKNOWN
License-File: LICENSE
